mailgun2/__init__.py
mailgun2/__version__.py
mailgun2/mailgun.py
mailgun2/tests/__init__.py
mailgun2/tests/mailgun.py
mailgun2-2.0.1.dist-info/LICENSE
mailgun2-2.0.1.dist-info/METADATA
mailgun2-2.0.1.dist-info/WHEEL
mailgun2-2.0.1.dist-info/top_level.txt
mailgun2-2.0.1.dist-info/RECORD
