Metadata-Version: 2.1
Name: mailgun2
Version: 2.0.1
Summary: A python client for Mailgun API v2
Home-page: https://github.com/albertyw/python-mailgun2
Author: Albert Wang
Author-email: git@albertyw.com
License: Apache
Keywords: mailgun,email
Platform: UNKNOWN
Classifier: Development Status :: 5 - Production/Stable
Classifier: Environment :: Web Environment
Classifier: Intended Audience :: Telecommunications Industry
Classifier: License :: OSI Approved :: Apache Software License
Classifier: Programming Language :: Python
Classifier: Programming Language :: Python :: 3.7
Classifier: Programming Language :: Python :: 3.8
Classifier: Programming Language :: Python :: 3.9
Classifier: Programming Language :: Python :: 3.10
Classifier: Topic :: Communications :: Email
Classifier: Topic :: Software Development :: Libraries :: Python Modules
License-File: LICENSE
Requires-Dist: requests (<3.0,>=2.6)
Provides-Extra: dev
Provides-Extra: test
